bfopublisher/__init__.py
bfopublisher-0.0.2.dist-info/LICENSE
bfopublisher-0.0.2.dist-info/METADATA
bfopublisher-0.0.2.dist-info/WHEEL
bfopublisher-0.0.2.dist-info/top_level.txt
bfopublisher-0.0.2.dist-info/RECORD
