Metadata-Version: 2.1
Name: bfopublisher
Version: 0.0.2
Summary: Access a BFO Publisher web service
Home-page: https://publisher.bfo.com
Author: Chris Burdess
Author-email: chris@bfo.com
License: MIT
Download-URL: https://pypi.org/project/bfopublisher/
Platform: UNKNOWN
Classifier: Programming Language :: Python :: 3
Classifier: License :: OSI Approved :: MIT License
Classifier: Operating System :: OS Independent
Requires-Python: >=3
Requires-Dist: cbor2
Requires-Dist: websocket-client
